ultraclean/__init__.py
ultraclean/clean.py
ultraclean/predict.py
ultraclean-0.2.2.dist-info/LICENSE.rst
ultraclean-0.2.2.dist-info/METADATA
ultraclean-0.2.2.dist-info/WHEEL
ultraclean-0.2.2.dist-info/top_level.txt
ultraclean-0.2.2.dist-info/RECORD
