Metadata-Version: 2.1
Name: ultraclean
Version: 0.2.2
Summary: UltraClean is a fast and efficient Python library for cleaning and preprocessing text data for AI/ML tasks and data processing.
Home-page: https://github.com/Kawai-Senpai/UltraClean
Download-URL: https://github.com/Kawai-Senpai/UltraClean
Author: Ranit Bhowmick
Author-email: bhowmickranitking@duck.com
License: MIT License with attribution requirement
Keywords: Text Cleaning,Data Preprocessing,AI,ML,Spam Detection
Classifier: Development Status :: 3 - Alpha
Classifier: Intended Audience :: Developers
Classifier: Topic :: Software Development :: Libraries :: Python Modules
Classifier: License :: OSI Approved :: MIT License
Classifier: Programming Language :: Python :: 3.7
Classifier: Programming Language :: Python :: 3.8
Classifier: Programming Language :: Python :: 3.9
Classifier: Programming Language :: Python :: 3.10
Classifier: Programming Language :: Python :: 3.11
Classifier: Operating System :: OS Independent
Classifier: Typing :: Typed
Requires-Python: >=3.7
License-File: LICENSE.rst
Requires-Dist: transformers>=4.0.0
Requires-Dist: torch>=1.7.0
Requires-Dist: emoji>=1.2.0
Requires-Dist: tf-keras>=2.6.0
Provides-Extra: dev
Requires-Dist: pytest>=7.0.0; extra == "dev"
Requires-Dist: pytest-asyncio>=0.21.0; extra == "dev"
Requires-Dist: black>=22.0.0; extra == "dev"
Requires-Dist: mypy>=0.900; extra == "dev"
Requires-Dist: flake8>=4.0.0; extra == "dev"
Provides-Extra: docs
Requires-Dist: sphinx>=4.0.0; extra == "docs"
Requires-Dist: sphinx-rtd-theme>=1.0.0; extra == "docs"
